easymp/__init__.py
easymp/easymp.py
easymp-0.1.8.dist-info/LICENSE.txt
easymp-0.1.8.dist-info/METADATA
easymp-0.1.8.dist-info/WHEEL
easymp-0.1.8.dist-info/top_level.txt
easymp-0.1.8.dist-info/RECORD
