Metadata-Version: 2.1
Name: easymp
Version: 0.1.8
Summary: Python utility for easy multiprocessing + logging.
Home-page: https://github.com/MNayer/easymp
Author: MNayer
Author-email: marie.nayer@web.de
License: 0BSD
Keywords: multiprocessing logging
License-File: LICENSE.txt
